README.md
setup.py
example/__init__.py
example/base.py
example/index.py
example/users/__init__.py
example/users/create_user.py
example/users/edit_user.py
example/users/fetch_all_users.py
example/users/fetch_user_details.py
example/wallets/__init__.py
example/wallets/create_wallet.py
example/wallets/fetch_all_wallets.py
example/wallets/fetch_payment_address_by_id.py
quidax_python.egg-info/PKG-INFO
quidax_python.egg-info/SOURCES.txt
quidax_python.egg-info/dependency_links.txt
quidax_python.egg-info/requires.txt
quidax_python.egg-info/top_level.txt
quidaxapi/__init__.py
quidaxapi/base.py
quidaxapi/deposits.py
quidaxapi/instant_orders.py
quidaxapi/markets.py
quidaxapi/orders.py
quidaxapi/quidax.py
quidaxapi/quote.py
quidaxapi/trades.py
quidaxapi/users.py
quidaxapi/validate_address.py
quidaxapi/wallets.py
quidaxapi/withdrawals.py
quidaxapi/tests/__init__.py
quidaxapi/tests/base_test_case.py
quidaxapi/tests/test_base.py
quidaxapi/tests/test_deposits.py
quidaxapi/tests/test_instant_orders.py
quidaxapi/tests/test_markets.py
quidaxapi/tests/test_orders.py
quidaxapi/tests/test_quotes.py
quidaxapi/tests/test_trades.py
quidaxapi/tests/test_users.py
quidaxapi/tests/test_validate_address.py
quidaxapi/tests/test_wallets.py
quidaxapi/tests/test_withdrawals.py