Metadata-Version: 2.1
Name: quidax-python
Version: 1.2
Summary: A python library to consume Quidax API
Home-page: UNKNOWN
Author-email: oye@appstate.co
License: MIT
Keywords: quidax python library
Platform: UNKNOWN
Classifier: Development Status :: 4 - Beta
Classifier: Intended Audience :: Developers
Classifier: License :: OSI Approved :: MIT License
Classifier: Programming Language :: Python :: 3
Classifier: Programming Language :: Python :: 3.6
